odoo8_addon_project_task_materials_analytic_partner-8.0.1.0.0.99.dev10-py2.7-nspkg.pth
odoo8_addon_project_task_materials_analytic_partner-8.0.1.0.0.99.dev10.dist-info/DESCRIPTION.rst
odoo8_addon_project_task_materials_analytic_partner-8.0.1.0.0.99.dev10.dist-info/METADATA
odoo8_addon_project_task_materials_analytic_partner-8.0.1.0.0.99.dev10.dist-info/RECORD
odoo8_addon_project_task_materials_analytic_partner-8.0.1.0.0.99.dev10.dist-info/WHEEL
odoo8_addon_project_task_materials_analytic_partner-8.0.1.0.0.99.dev10.dist-info/metadata.json
odoo8_addon_project_task_materials_analytic_partner-8.0.1.0.0.99.dev10.dist-info/namespace_packages.txt
odoo8_addon_project_task_materials_analytic_partner-8.0.1.0.0.99.dev10.dist-info/top_level.txt
odoo_addons/project_task_materials_analytic_partner/README.rst
odoo_addons/project_task_materials_analytic_partner/__init__.py
odoo_addons/project_task_materials_analytic_partner/__openerp__.py
odoo_addons/project_task_materials_analytic_partner/i18n/de.po
odoo_addons/project_task_materials_analytic_partner/i18n/es.po
odoo_addons/project_task_materials_analytic_partner/i18n/es_MX.po
odoo_addons/project_task_materials_analytic_partner/i18n/fi.po
odoo_addons/project_task_materials_analytic_partner/i18n/fr.po
odoo_addons/project_task_materials_analytic_partner/i18n/it.po
odoo_addons/project_task_materials_analytic_partner/i18n/nl.po
odoo_addons/project_task_materials_analytic_partner/i18n/project_task_materials_analytic_partner.pot
odoo_addons/project_task_materials_analytic_partner/i18n/pt.po
odoo_addons/project_task_materials_analytic_partner/i18n/pt_BR.po
odoo_addons/project_task_materials_analytic_partner/i18n/sl.po
odoo_addons/project_task_materials_analytic_partner/models/__init__.py
odoo_addons/project_task_materials_analytic_partner/models/project_task_materials_analytic_partner.py
odoo_addons/project_task_materials_analytic_partner/static/description/icon.png
odoo_addons/project_task_materials_analytic_partner/tests/__init__.py
odoo_addons/project_task_materials_analytic_partner/tests/test_project_task_materials_analytic_partner.py
odoo_addons/project_task_materials_analytic_partner/views/project_view.xml
